[{
        "category": "Beverage",
        "contents": [{
                "isAvailable": true,
                "name": "Mug Root Beer",
                "code": "MRB",
                "color": "#D1B090",
                "sizes": [{
                        "name": "medium",
                        "code": "MD",
                        "price": 99
                    },
                    {
                        "name": "large",
                        "code": "LG",
                        "price": 115
                    }
                ]
            },
            {
                "isAvailable": true,
                "name": "Mug Root Beer Float",
                "code": "MRBFLT",
                "color": "#E4D3A2",
                "sizes": [{
                    "name": "normal",
                    "code": "N",
                    "price": 66
                }]
            },
            {
                "isAvailable": true,
                "name": "Coke Zero",
                "code": "CZ",
                "color": "#808080",
                "sizes": [{
                        "name": "medium",
                        "code": "MD",
                        "price": 115
                    },
                    {
                        "name": "large",
                        "code": "LG",
                        "price": 99
                    }
                ]
            },
            {
                "isAvailable": true,
                "name": "Orange Juice",
                "code": "OJ",
                "color": "#FFB84D",
                "sizes": [{
                        "name": "medium",
                        "code": "MD",
                        "price": 102
                    },
                    {
                        "name": "large",
                        "code": "LG",
                        "price": 111
                    }
                ]
            },
            {
                "isAvailable": true,
                "name": "Apple Juice",
                "code": "AJ",
                "color": "#C8E4B1",
                "sizes": [{
                        "name": "medium",
                        "code": "MD",
                        "price": 102
                    },
                    {
                        "name": "large",
                        "code": "LG",
                        "price": 112
                    }
                ]
            },
            {
                "isAvailable": true,
                "name": "Sarsi Float",
                "code": "SARSFLT",
                "color": "#C84C4C",
                "sizes": [{
                    "name": "normal",
                    "code": "N",
                    "price": 62
                }]
            },
            {
                "isAvailable": true,
                "name": "Regular Sarsi",
                "code": "SARS",
                "color": "#C84C4C",
                "sizes": [{
                    "name": "normal",
                    "code": "N",
                    "price": 113
                }]
            },
            {
                "isAvailable": true,
                "name": "Coke Float",
                "code": "COKEFLT",
                "color": "#E55A47",
                "sizes": [{
                    "name": "normal",
                    "code": "N",
                    "price": 67
                }]
            },
            {
                "isAvailable": true,
                "name": "Lipton Ice Tea",
                "code": "LIPT",
                "color": "#F4E58A",
                "sizes": [{
                        "name": "normal",
                        "code": "N",
                        "price": 98
                    },
                    {
                        "name": "large",
                        "code": "LG",
                        "price": 112
                    }
                ]
            },
            {
                "isAvailable": true,
                "name": "Iced Black Coffee",
                "code": "IBC",
                "color": "#7F5F75",
                "sizes": [{
                        "name": "medium",
                        "code": "MD",
                        "price": 84
                    },
                    {
                        "name": "large",
                        "code": "LG",
                        "price": 109
                    }
                ]
            },
            {
                "isAvailable": true,
                "name": "Iced Vanilla Coffee",
                "code": "IVC",
                "color": "#D4C4B7",
                "sizes": [{
                        "name": "medium",
                        "code": "MD",
                        "price": 99
                    },
                    {
                        "name": "large",
                        "code": "LG",
                        "price": 120
                    }
                ]
            },
            {
                "isAvailable": true,
                "name": "Ice Mocha Coffee",
                "code": "IMC",
                "color": "#7F4B76",
                "sizes": [{
                        "name": "medium",
                        "code": "MD",
                        "price": 99
                    },
                    {
                        "name": "large",
                        "code": "LG",
                        "price": 120
                    }
                ]
            },
            {
                "isAvailable": true,
                "name": "Roast Coffee",
                "code": "RC",
                "color": "#6F4F2F",
                "sizes": [{
                    "name": "cup",
                    "code": "CP",
                    "price": 65
                }]
            }
        ]
    },

    {
        "category": "Meals",
        "contents": [{
                "isAvailable": true,
                "name": "BLT Chicken King (spicy flavor) Meal",
                "code": "BLTCKSPCYML",
                "price": 322,
                "color": "#FFCCCC"
            },
            {
                "isAvailable": true,
                "name": "BLT Chicken King (spicy flavor) Solo",
                "code": "BLTCKSPCYSOLO",
                "price": 253,
                "color": "#FFCCCC"
            },
            {
                "isAvailable": true,
                "name": "Truffle Whopper (Junior) Combo",
                "code": "TRFLJRCMB",
                "price": 265,
                "color": "#FFF9CC"
            },
            {
                "isAvailable": true,
                "name": "Truffle Whopper (Junior) Solo",
                "code": "TRFLJRSOLO",
                "price": 179,
                "color": "#FFF9CC"
            },
            {
                "isAvailable": true,
                "name": "Truffle Whopper Combo",
                "code": "TRFLCMB",
                "price": 391,
                "color": "#FFF9CC"
            },
            {
                "isAvailable": true,
                "name": "Truffle Whopper Solo",
                "code": "TRFLSOLO",
                "price": 314,
                "color": "#FFF9CC"
            },
            {
                "isAvailable": true,
                "name": "1PC Chunky Chicken Fillet Creamy Parm Combo",
                "code": "1CKPARMCMB",
                "price": 125,
                "color": "#FFF9CC"
            },
            {
                "isAvailable": true,
                "name": "1PC Chunky Chicken Fillet Creamy Parm Solo",
                "code": "1CKPARMSOLO",
                "price": 105,
                "color": "#FFF9CC"
            },
            {
                "isAvailable": true,
                "name": "2PCS Chunky Chicken Fillet Creamy Parm Combo",
                "code": "2CKPARMCMB",
                "price": 175,
                "color": "#FFF9CC"
            },
            {
                "isAvailable": true,
                "name": "2PCS Chunky Chicken Fillet Creamy Parm Solo",
                "code": "2CKPARMSOLO",
                "price": 155,
                "color": "#FFF9CC"
            },
            {
                "isAvailable": true,
                "name": "Chicken Chunky Fillet (1 PC) with Rice",
                "code": "CK1WRC",
                "price": 105,
                "color": "#ed7902"
            },
            {
                "isAvailable": true,
                "name": "Chicken Chunky Fillet (2 PCS) with Rice",
                "code": "CK2WRC",
                "price": 170,
                "color": "#ed7902"
            },
            {
                "isAvailable": true,
                "name": "Chicken Chunky Fillet (2 PCS) with Rice + Drink",
                "code": "CK2CMBRC",
                "price": 172,
                "color": "#ed7902"
            },
            {
                "isAvailable": true,
                "name": "4 piece Nuggets with Rice (value deal)",
                "code": "4PCNUGRC",
                "price": 181,
                "color": "#F4C542"
            },
            {
                "isAvailable": true,
                "name": "6-pc Nuggets with special sauces + Drink",
                "code": "6PCNUGSAUCEDRINK",
                "price": 249,
                "color": "#F4C542"
            },
            {
                "isAvailable": true,
                "name": "6-pc Nuggets combo with Rice",
                "code": "6PCNUGRC",
                "price": 249,
                "color": "#F4C542"
            },
            {
                "isAvailable": true,
                "name": "1-piece Chicken Thigh with Rice",
                "code": "1PCTHWRICE",
                "price": 280,
                "color": "#B57B57"
            },
            {
                "isAvailable": true,
                "name": "2-pieces of Chicken Thigh with Rice meal",
                "code": "2PCTHWRICEML",
                "price": 397,
                "color": "#B57B57"
            },
            {
                "isAvailable": true,
                "name": "2 pieces chicken leg piece with Rice",
                "code": "2PCLWRICE",
                "price": 368,
                "color": "#B57B57"
            }
        ]
    },
    {
        "category": "Whopper",
        "contents": [{
                "isAvailable": true,
                "name": "Pepperoni Bacon Whopper – Jr Solo",
                "code": "PBWJRNSOLO",
                "price": 261,
                "color": "#ed7902"
            },
            {
                "isAvailable": true,
                "name": "Pepperoni Bacon Whopper Jr Meal",
                "code": "PBWJRNCMB",
                "price": 333,
                "color": "#ed7902"
            },
            {
                "isAvailable": true,
                "name": "Pepperoni Bacon Whopper Solo",
                "code": "PBWLGSOLO",
                "price": 428,
                "color": "#ed7902"
            },
            {
                "isAvailable": true,
                "name": "Pepperoni Bacon Whopper Meal",
                "code": "PBWLGCMB",
                "price": 499,
                "color": "#ed7902"
            },
            {
                "isAvailable": true,
                "name": "Whopper Junior",
                "code": "WHJRNR",
                "price": 93,
                "color": "#ed7902"
            },
            {
                "isAvailable": true,
                "name": "Whopper Junior Combo",
                "code": "WHJRNRCMB",
                "price": 205,
                "color": "#ed7902"
            },
            {
                "isAvailable": true,
                "name": "Whopper Meal",
                "code": "WHMRL",
                "price": 314,
                "color": "#ed7902"
            },
            {
                "isAvailable": true,
                "name": "Whopper Solo",
                "code": "WHWPRSOLO",
                "price": 246,
                "color": "#ed7902"
            },
            {
                "isAvailable": true,
                "name": "4 Layered Cheese Whopper",
                "code": "4LCW",
                "price": 312,
                "color": "#FFF9B3"
            },
            {
                "isAvailable": true,
                "name": "4 Layered Cheese Whopper Meal Combo",
                "code": "4LCWMC",
                "price": 370,
                "color": "#FFF9B3"
            },
            {
                "isAvailable": true,
                "name": "4 Layers of Cheese – Whopper Junior",
                "code": "4LCWJ",
                "price": 136,
                "color": "#FFF9B3"
            },
            {
                "isAvailable": true,
                "name": "4 Layers of Cheese – Whopper Junior Meal",
                "code": "4LCWJM",
                "price": 214,
                "color": "#FFF9B3"
            },
            {
                "isAvailable": true,
                "name": "Bacon 4-Cheese Whopper",
                "code": "B4CW",
                "price": 449,
                "color": "#FFF9B3"
            },
            {
                "isAvailable": true,
                "name": "Bacon 4-Cheese Whopper Meal Combo",
                "code": "B4CWMC",
                "price": 518,
                "color": "#FFF9B3"
            },
            {
                "isAvailable": true,
                "name": "Junior Bacon 4-Cheese Whopper",
                "code": "JB4CW",
                "price": 281,
                "color": "#FFF9B3"
            },
            {
                "isAvailable": true,
                "name": "Junior Bacon 4-Cheese Whopper Combo",
                "code": "JB4CWCOMBO",
                "price": 359,
                "color": "#FFF9B3"
            }
        ]
    }, {
        "category": "Flame-grilled",
        "contents": [{
                "isAvailable": true,
                "name": "BBQ Bacon Cheese Burger Solo",
                "code": "BBQBCHEESEBURGER1",
                "price": 249,
                "color": "#FF6F00"
            },
            {
                "isAvailable": true,
                "name": "BBQ Bacon Cheese Burger Combo",
                "code": "BBQBCHEESEBURGERCMB",
                "price": 329,
                "color": "#FF6F00"
            },
            {
                "isAvailable": true,
                "name": "Double BBQ Bacon cheeseburger Combo",
                "code": "DBBQBCHEESEBURGERCMB",
                "price": 440,
                "color": "#FF6F00"
            },
            {
                "isAvailable": true,
                "name": "Double BBQ Bacon cheeseburger Solo",
                "code": "DBBQBCHEESEBURGERSOLO",
                "price": 374,
                "color": "#FF6F00"
            },
            {
                "isAvailable": true,
                "name": "Hamburger Meal",
                "code": "HAMBRGRMEAL",
                "price": 170,
                "color": "#D14B2E"
            },
            {
                "isAvailable": true,
                "name": "Solo Hamburger",
                "code": "SOLOHAMBRGR",
                "price": 101,
                "color": "#D14B2E"
            },
            {
                "isAvailable": true,
                "name": "Barbeque Hamburger Meal",
                "code": "BBQHAMBRGRMEAL",
                "price": 150,
                "color": "#D14B2E"
            },
            {
                "isAvailable": true,
                "name": "Solo Barbeque Hamburger",
                "code": "SOLOBBQHAMBRGR",
                "price": 89,
                "color": "#D14B2E"
            },
            {
                "isAvailable": true,
                "name": "Quarter Pound King Meal Combo",
                "code": "QTRPNDKINGMEALCMB",
                "price": 398,
                "color": "#D14B2E"
            },
            {
                "isAvailable": true,
                "name": "Quarter Pound King Solo",
                "code": "QTRPNDKINGSOLO",
                "price": 330,
                "color": "#D14B2E"
            },
            {
                "isAvailable": true,
                "name": "Double Quarter Pound King Meal Combo",
                "code": "DQTRPNDKINGMEALCMB",
                "price": 551,
                "color": "#D14B2E"
            },
            {
                "isAvailable": true,
                "name": "Double Quarter Pound King Meal",
                "code": "DQTRPNDKINGMEAL1",
                "price": 483,
                "color": "#D14B2E"
            },
            {
                "isAvailable": true,
                "name": "Regular Cheese Burger Flame Grilled Meal",
                "code": "REGCHEESEBURGERFLAMECMB",
                "price": 165,
                "color": "#FFD700"
            },
            {
                "isAvailable": true,
                "name": "Regular Cheese Burger Flame Grilled Solo",
                "code": "REGCHEESEBURGERFLAMESOLO",
                "price": 89,
                "color": "#FFD700"
            },
            {
                "isAvailable": true,
                "name": "Double Cheese Burger Flame Grilled Meal",
                "code": "DBLRCHEESEBURGERFLAMECMB",
                "price": 404,
                "color": "#FFD700"
            },
            {
                "isAvailable": true,
                "name": "Double Cheese Burger Flame Grilled Solo",
                "code": "DBLRCHEESEBURGERFLAMESOLO",
                "price": 350,
                "color": "#FFD700"
            },
            {
                "isAvailable": true,
                "name": "Triple Cheese Burger Flame Grilled Combo",
                "code": "TRIPLECHEESEBURGERFLAMECMB",
                "price": 422,
                "color": "#FFD700"
            },
            {
                "isAvailable": true,
                "name": "Triple Cheese Burger Flame Grilled Solo",
                "code": "TRIPLECHEESEBURGERFLAMESOLO",
                "price": 381,
                "color": "#FFD700"
            },
            {
                "isAvailable": true,
                "name": "Flame Grilled Quadrupled Cheese Burger Solo",
                "code": "FLAMEGRILLEDQUADCHEESEBURGER1",
                "price": 477,
                "color": "#FFD700"
            },
            {
                "isAvailable": true,
                "name": "Flame Grilled Quadrupled Cheese Burger Combo",
                "code": "FLAMEGRILLEDQUADCHEESEBURGERCMB",
                "price": 545,
                "color": "#FFD700"
            }
        ]
    }, {
        "category": "Delicious Sides",
        "contents": [{
                "isAvailable": true,
                "name": "10 piece Crunchy Chicken Nuggets",
                "code": "10PCNUGGETS",
                "price": 273,
                "color": "#F4C542"
            },
            {
                "isAvailable": true,
                "name": "Chicken Nuggets (4 pieces) with Drink",
                "code": "4PCNUGWITHDRINK",
                "price": 147,
                "color": "#F4C542"
            },
            {
                "isAvailable": true,
                "name": "Chicken Nuggets (4 pieces)",
                "code": "4PCNUGGETS",
                "price": 120,
                "color": "#F4C542"
            },
            {
                "isAvailable": true,
                "name": "4 piece Nuggets with side meal (choose any sauce)",
                "code": "4PCNUGWITHSAUCEMEAL",
                "price": 181,
                "color": "#F4C542"
            },
            {
                "isAvailable": true,
                "name": "Cheese Bites (6 pieces)",
                "code": "CHEESEBITES6",
                "price": 143,
                "color": "#FFCC00"
            },
            {
                "isAvailable": true,
                "name": "Cheese Bites (10 pieces)",
                "code": "CHEESEBITES10",
                "price": 211,
                "color": "#FFCC00"
            },
            {
                "isAvailable": true,
                "name": "Onion Rings (King’s Bucket)",
                "code": "ONIONRINGSKB",
                "price": 268,
                "color": "#FF8C00"
            },
            {
                "isAvailable": true,
                "name": "King’s Bucket French Fries",
                "code": "FRENCHFRIESKB",
                "price": 233,
                "color": "#FF8C00"
            },
            {
                "isAvailable": true,
                "name": "Hash Bites",
                "code": "HASHBITES",
                "price": 233,
                "color": "#FF8C00"
            },
            {
                "isAvailable": true,
                "name": "BK French Fries – Regular size",
                "code": "BKFRIESREGULAR",
                "price": 65,
                "color": "#FF8C00"
            },
            {
                "isAvailable": true,
                "name": "BK French Fries – Medium",
                "code": "BKFRIESMEDIUM",
                "price": 108,
                "color": "#FF8C00"
            },
            {
                "isAvailable": true,
                "name": "BK French Fries – Large",
                "code": "BKFRIESLARGE",
                "price": 137,
                "color": "#FF8C00"
            },
            {
                "isAvailable": true,
                "name": "BK Onion Rings, Medium size",
                "code": "BKONIONRINGSMEDIUM",
                "price": 83,
                "color": "#FF8C00"
            },
            {
                "isAvailable": true,
                "name": "BK Onion Rings, Regular",
                "code": "BKONIONRINGSREGULAR",
                "price": 125,
                "color": "#FF8C00"
            },
            {
                "isAvailable": true,
                "name": "Onion Rings, large",
                "code": "ONIONRINGSLARGE",
                "price": 152,
                "color": "#FF8C00"
            }
        ]
    }, {
        "category": "Chicken Burgers",
        "contents": [{
                "isAvailable": true,
                "name": "BLT Chicken Burger Spicy Solo",
                "code": "BLTSPICY",
                "price": 253,
                "color": "#D14B2E"
            },
            {
                "isAvailable": true,
                "name": "BLT Chicken Burger Spicy Meal",
                "code": "BLTSPICYSET",
                "price": 323,
                "color": "#D14B2E"
            },
            {
                "isAvailable": true,
                "name": "Crunchy Chicken Burger Solo",
                "code": "CRCHKN",
                "price": 245,
                "color": "#FF6F00"
            },
            {
                "isAvailable": true,
                "name": "Crunchy Chicken Burger Meal",
                "code": "CRCHKNSET",
                "price": 312,
                "color": "#FF6F00"
            },
            {
                "isAvailable": true,
                "name": "Spicy Chicken King Burger Solo",
                "code": "SPCKNG",
                "price": 261,
                "color": "#D14B2E"
            },
            {
                "isAvailable": true,
                "name": "Spicy Chicken King Burger Meal",
                "code": "SPCKNGSET",
                "price": 326,
                "color": "#D14B2E"
            },
            {
                "isAvailable": true,
                "name": "X-tra Long Chicken Sandwich Solo (Large)",
                "code": "XLCHKSOLLG",
                "price": 167,
                "color": "#FF6F00"
            },
            {
                "isAvailable": true,
                "name": "X-tra Long Chicken Sandwich Combo Deal (Large)",
                "code": "XLCHKCMBO",
                "price": 233,
                "color": "#FF6F00"
            },
            {
                "isAvailable": true,
                "name": "Junior X-tra Long Chicken Sandwich Solo",
                "code": "JXLCHKSOL",
                "price": 74,
                "color": "#FF6F00"
            },
            {
                "isAvailable": true,
                "name": "Junior X-tra Long Chicken Sandwich Combo Deal",
                "code": "JXLCHKCMBO",
                "price": 169,
                "color": "#FF6F00"
            }
        ]
    }, {
        "category": "King Breakfast",
        "contents": [{
                "isAvailable": true,
                "name": "Sausage Waffle with Cheese Solo",
                "code": "SWCHS",
                "price": 211,
                "color": "#F4A261"
            },
            {
                "isAvailable": true,
                "name": "Sausage Waffle with Egg Combo Meal",
                "code": "SWEGGCM",
                "price": 296,
                "color": "#F4A261"
            },
            {
                "isAvailable": true,
                "name": "Sausage Waffle with Egg Solo Meal",
                "code": "SWEGGSOLO",
                "price": 224,
                "color": "#F4A261"
            },
            {
                "isAvailable": true,
                "name": "2-pc Waffle with Maple Combo",
                "code": "2WFLMAPCM",
                "price": 204,
                "color": "#F4A261"
            },
            {
                "isAvailable": true,
                "name": "2-pc Waffle with Maple + Sausage Solo",
                "code": "2WFLMAPS",
                "price": 211,
                "color": "#F4A261"
            },
            {
                "isAvailable": true,
                "name": "2-pc Waffle with Maple + Sausage Combo Meal",
                "code": "2WFLMAPSCM",
                "price": 284,
                "color": "#F4A261"
            },
            {
                "isAvailable": true,
                "name": "2-pc Waffle with Maple Solo",
                "code": "2WFLMAPSOLO",
                "price": 131,
                "color": "#F4A261"
            },
            {
                "isAvailable": true,
                "name": "Waffle Sausage and Cheese Combo Feast",
                "code": "WSCHSCF",
                "price": 284,
                "color": "#F4A261"
            }
        ]
    }, {
        "category": "Plant-Based",
        "contents": [{
                "isAvailable": true,
                "name": "Organic Plant Based Whopper Solo (Large)",
                "code": "PBWHSOLOLG",
                "price": 340,
                "color": "#4CAF50"
            },
            {
                "isAvailable": true,
                "name": "Organic Plant Based Whopper Combo Deal (Large)",
                "code": "PBWHCMBO",
                "price": 404,
                "color": "#4CAF50"
            },
            {
                "isAvailable": true,
                "name": "Junior Organic Plant Based Whopper Solo",
                "code": "JPBWHSOLO",
                "price": 141,
                "color": "#4CAF50"
            },
            {
                "isAvailable": true,
                "name": "Junior Organic Plant Based Whopper Combo Deal",
                "code": "JPBWHCMBO",
                "price": 215,
                "color": "#4CAF50"
            }
        ]
    }, {
        "category": "Kings Specials",
        "contents": [{
                "isAvailable": true,
                "name": "Barbecue Bacon Burger – Solo",
                "code": "BBQBAKINGBURGER",
                "price": 470,
                "color": "#FFB74D"
            },
            {
                "isAvailable": true,
                "name": "Barbecue Bacon Burger – Meal",
                "code": "BBQBAKINGBURGERSET",
                "price": 551,
                "color": "#FFB74D"
            },
            {
                "isAvailable": true,
                "name": "Bacon King Burger – Solo (junior size)",
                "code": "BKINGBURGERJUNIOR",
                "price": 297,
                "color": "#FF7043"
            },
            {
                "isAvailable": true,
                "name": "Bacon King Burger – Meal (junior size)",
                "code": "BKINGBURGERJUNIORSET",
                "price": 368,
                "color": "#FF7043"
            },
            {
                "isAvailable": true,
                "name": "Bacon King Burger – Solo (large size)",
                "code": "BKINGBURGERLARGE",
                "price": 470,
                "color": "#FF7043"
            },
            {
                "isAvailable": true,
                "name": "Bacon King Burger – Meal (large size)",
                "code": "BKINGBURGERLARGESET",
                "price": 540,
                "color": "#FF7043"
            },
            {
                "isAvailable": true,
                "name": "Junior Double Bacon Burger – Solo",
                "code": "JUNIORDBB",
                "price": 374,
                "color": "#FF5722"
            },
            {
                "isAvailable": true,
                "name": "Junior Double Bacon Burger – Meal",
                "code": "JUNIORDBBSET",
                "price": 449,
                "color": "#FF5722"
            },
            {
                "isAvailable": true,
                "name": "Double Bacon Burger – Solo (large)",
                "code": "DBBXLARGE",
                "price": 606,
                "color": "#FF5722"
            },
            {
                "isAvailable": true,
                "name": "Double Bacon Burger – Meal (large)",
                "code": "DBBXLARGEBUNDLE",
                "price": 674,
                "color": "#FF5722"
            },
            {
                "isAvailable": true,
                "name": "Double BBQ Bacon Jr. – Solo",
                "code": "DBBQBJUNIOR",
                "price": 374,
                "color": "#FF7043"
            },
            {
                "isAvailable": true,
                "name": "Double BBQ Bacon Jr. – Meal",
                "code": "DBBQBJUNIORSET",
                "price": 443,
                "color": "#FF7043"
            },
            {
                "isAvailable": true,
                "name": "Double BBQ Bacon – Solo (single classic)",
                "code": "DBBQBLARGEC",
                "price": 605,
                "color": "#FF7043"
            },
            {
                "isAvailable": true,
                "name": "Double BBQ Bacon – Meal (large)",
                "code": "DBBQBLARGEMEAL",
                "price": 675,
                "color": "#FF7043"
            },
            {
                "isAvailable": true,
                "name": "Swiss Mushroom Jr. – Solo",
                "code": "SWISSHROOMJUNIOR",
                "price": 272,
                "color": "#8D6E63"
            },
            {
                "isAvailable": true,
                "name": "Swiss Mushroom Jr. – Meal",
                "code": "SWISSHROOMJUNIORSET",
                "price": 347,
                "color": "#8D6E63"
            },
            {
                "isAvailable": true,
                "name": "Double Swiss Mushroom Jr. – Solo",
                "code": "DBLSWISSHROOMJUNIOR",
                "price": 363,
                "color": "#8D6E63"
            },
            {
                "isAvailable": true,
                "name": "Double Swiss Mushroom Jr. – Meal",
                "code": "DBLSWISSHROOMJUNIORSET",
                "price": 438,
                "color": "#8D6E63"
            }
        ]
    }, {
        "category": "Group Meals",
        "contents": [{
                "isAvailable": true,
                "name": "Mix n feast for 2 People <br> choose 2 mains of your choice, 2 sides, 2 drinks and 4 pieces of chicken nuggets",
                "code": "MNF2P",
                "price": 448,
                "color": "#FF6F00"
            },
            {
                "isAvailable": true,
                "name": "Mix n feast for 3 People <br> choose 3 main of your choice, 3 side dishes, 3 drinks and 6 pieces of chicken nuggets",
                "code": "MNF3P",
                "price": 658,
                "color": "#FF6F00"
            },
            {
                "isAvailable": true,
                "name": "Mix n feast for 4 People <br> choose 4 main dishes of your choice, 4 sides, 4 drinks & 10 pieces of chicken nuggets",
                "code": "MNF4P",
                "price": 888,
                "color": "#FF6F00"
            },
            {
                "isAvailable": true,
                "name": "2 X-Tra Long Chicken Jr. + 2 Flame Grilled cheese burgers + 2 King’s bucket + 4 Drinks",
                "code": "XTLG4P",
                "price": 799,
                "color": "#FFD700"
            },
            {
                "isAvailable": true,
                "name": "2 Junior Whopper + 2 x-tra long chicken sandwich Jr. + 2 King’s bucket + 4 Drinks",
                "code": "JWXT4P",
                "price": 845,
                "color": "#FF6F00"
            },
            {
                "isAvailable": true,
                "name": "2 plant based Junior Whopper, 1 King’s bucket and 2 Drinks",
                "code": "PBJW1K2D",
                "price": 524,
                "color": "#6B8E23"
            },
            {
                "isAvailable": true,
                "name": "2 long chicken sandwich Jr., 1 King’s bucket & 2 Drinks",
                "code": "LCSJ1K2D",
                "price": 418,
                "color": "#FF6F00"
            },
            {
                "isAvailable": true,
                "name": "2, 4-Cheese Junior Whopper plus 1 King’s bucket & 2 Drinks",
                "code": "4CJW1K2D",
                "price": 485,
                "color": "#FFD700"
            },
            {
                "isAvailable": true,
                "name": "Flame grilled cheese burger, Junior Whopper, 1 King’s bucket & 2 Drinks",
                "code": "FGCBJW1K2D",
                "price": 435,
                "color": "#FFD700"
            }
        ]
    }












]